graphwork/__init__.py
graphwork/audiovideo.py
graphwork/network.py
graphwork/plots.py
graphwork/recommendation.py
graphwork/seaborn.py
graphwork-0.1.1.dist-info/METADATA
graphwork-0.1.1.dist-info/WHEEL
graphwork-0.1.1.dist-info/top_level.txt
graphwork-0.1.1.dist-info/RECORD
