Metadata-Version: 2.4
Name: graphwork
Version: 0.1.1
Summary: A simple package with HTML files included.
Author: schz
Requires-Python: >=3.8
Requires-Dist: opencv-python
Requires-Dist: pillow
Requires-Dist: numpy
Requires-Dist: librosa
Requires-Dist: matplotlib
Requires-Dist: pandas
Requires-Dist: scikit-learn
Requires-Dist: networkx
Requires-Dist: scipy
Dynamic: author
Dynamic: requires-dist
Dynamic: requires-python
Dynamic: summary
